{"law_id":"177","section_number":"8-2015","catch_line":"DUTY TO REPORT DAMAGE.","history":"","order_by":"8-2015","metadata":false,"url":"\/8-2015\/","token":"8-2015","structure":{"1":{"id":"89","name":"ARTICLE A. - GENERAL PROVISIONS","identifier":"A","label":"article","url":"\/II\/8\/2\/A\/"},"2":{"id":"88","name":"CHAPTER 2. - WATER AND SEWER SERVICE","identifier":"2","label":"chapter","url":"\/II\/8\/2\/"},"3":{"id":"84","name":"PART 8 - PUBLIC UTILITIES","identifier":"8","label":"part","url":"\/II\/8\/"},"4":{"id":"5","name":"Division II - Planning and Development","identifier":"II","label":"division","url":"\/II\/"}},"referred_to_by":{"0":{"id":"174","section_number":"8-2012","catch_line":"ACCESS TO AND OBSTRUCTIONS OF MANHOLES AND EASEMENTS.","url":"http:\/\/localhost:8888\/8-2012\/"}},"edition_id":"1","section_id":"177","structure_id":"89","full_text":"Every person who observes damage to a manhole or to any other part of the sanitary sewer system has a duty to report the damage to the Public Utilities Department. \n(Ord. No. 1999-658, \u00a72, 10-19-99)","text":{"0":{"id":"540","text":"Every person who observes damage to a manhole or to any other part of the sanitary sewer system has a duty to report the damage to the Public Utilities Department. \n(Ord. No. 1999-658, \u00a72, 10-19-99)","type":"section","prefixes":[""],"prefix":"","entire_prefix":"","prefix_anchor":"","level":1}},"ancestry":{"1":{"id":"89","name":"ARTICLE A. - GENERAL PROVISIONS","identifier":"A","label":"article","url":"\/II\/8\/2\/A\/"},"2":{"id":"88","name":"CHAPTER 2. - WATER AND SEWER SERVICE","identifier":"2","label":"chapter","url":"\/II\/8\/2\/"},"3":{"id":"84","name":"PART 8 - PUBLIC UTILITIES","identifier":"8","label":"part","url":"\/II\/8\/"},"4":{"id":"5","name":"Division II - Planning and Development","identifier":"II","label":"division","url":"\/II\/"}},"structure_contents":{"0":{"id":"162","structure_id":"89","section_number":"8-2001","catch_line":"DEFINITIONS.","url":"\/8-2001\/","token":"8-2001"},"1":{"id":"163","structure_id":"89","section_number":"8-2002","catch_line":"CONNECTING WITH WATER PIPES.","url":"\/8-2002\/","token":"8-2002"},"2":{"id":"164","structure_id":"89","section_number":"8-2003","catch_line":"REPLACEMENT OF WATER OR SEWER SERVICE STUBS.","url":"\/8-2003\/","token":"8-2003"},"3":{"id":"165","structure_id":"89","section_number":"8-2004","catch_line":"RESPONSIBILITY FOR MAKING CONNECTIONS.","url":"\/8-2004\/","token":"8-2004"},"4":{"id":"166","structure_id":"89","section_number":"8-2005","catch_line":"METER REQUIREMENTS; PLACEMENT OF METERS.","url":"\/8-2005\/","token":"8-2005"},"5":{"id":"167","structure_id":"89","section_number":"8-2006","catch_line":"ADDITIONAL METERS; COMMON CONNECTIONS; ALLOWED USES.","url":"\/8-2006\/","token":"8-2006"},"6":{"id":"168","structure_id":"89","section_number":"8-2007","catch_line":"COMMON METERS AND CONNECTIONS; REQUIREMENTS.","url":"\/8-2007\/","token":"8-2007"},"7":{"id":"169","structure_id":"89","section_number":"8-2008","catch_line":"WELLS; PERMIT REQUIRED.","url":"\/8-2008\/","token":"8-2008"},"8":{"id":"171","structure_id":"89","section_number":"8-2009","catch_line":"NEW OR REPLACEMENT WATER AND SEWER SYSTEMS TO BE FLOOD-RESISTANT.","url":"\/8-2009\/","token":"8-2009"},"9":{"id":"172","structure_id":"89","section_number":"8-2010","catch_line":"EMERGENCY DISCONTINUATION OF SERVICE AND REPAIRS.","url":"\/8-2010\/","token":"8-2010"},"10":{"id":"173","structure_id":"89","section_number":"8-2011","catch_line":"PAYMENT OF FEES AND CHARGES.","url":"\/8-2011\/","token":"8-2011"},"11":{"id":"174","structure_id":"89","section_number":"8-2012","catch_line":"ACCESS TO AND OBSTRUCTIONS OF MANHOLES AND EASEMENTS.","url":"\/8-2012\/","token":"8-2012"},"12":{"id":"175","structure_id":"89","section_number":"8-2013","catch_line":"INJURY TO SYSTEMS; REMOVING, DAMAGING, BREAKING, ETC.","url":"\/8-2013\/","token":"8-2013"},"13":{"id":"176","structure_id":"89","section_number":"8-2014","catch_line":"ENFORCEMENT PROCEDURE.","url":"\/8-2014\/","token":"8-2014"},"14":{"id":"177","structure_id":"89","section_number":"8-2015","catch_line":"DUTY TO REPORT DAMAGE.","url":"\/8-2015\/","token":"8-2015"},"15":{"id":"178","structure_id":"89","section_number":"8-2016","catch_line":"RALEIGH PUBLIC UTILITIES HANDBOOK.","url":"\/8-2016\/","token":"8-2016"},"16":{"id":"179","structure_id":"89","section_number":"8-2017","catch_line":"RESERVED.","url":"\/8-2017\/","token":"8-2017"},"17":{"id":"180","structure_id":"89","section_number":"8-2017","catch_line":"RESERVED. ","url":"\/8-2017\/","token":"8-2017"}},"previous_section":{"id":"176","structure_id":"89","section_number":"8-2014","catch_line":"ENFORCEMENT PROCEDURE.","url":"\/8-2014\/","token":"8-2014"},"next_section":{"id":"178","structure_id":"89","section_number":"8-2016","catch_line":"RALEIGH PUBLIC UTILITIES HANDBOOK.","url":"\/8-2016\/","token":"8-2016"},"references":false,"formats":{"txt":"\/8-2015.txt","json":"\/8-2015.xml"},"dublin_core":{"Title":"DUTY TO REPORT DAMAGE.","Type":"Text","Format":"text\/html","Identifier":"\u00a7 8-2015","Relation":"Code of State"},"plain_text":"                                  CODE OF STATE\n\nDUTY TO REPORT DAMAGE. (\u00a7 8-2015)\n\nEvery person who observes damage to a manhole or to any other part of the\nsanitary sewer system has a duty to report the damage to the Public Utilities\nDepartment. \n(Ord. No. 1999-658, \u00a72, 10-19-99)\n"}